peekingduck/__init__.py
peekingduck/cli.py
peekingduck/config_loader.py
peekingduck/declarative_loader.py
peekingduck/optional_requirements.txt
peekingduck/runner.py
peekingduck/commands/__init__.py
peekingduck/commands/core.py
peekingduck/commands/create_node.py
peekingduck/commands/create_node_helper.py
peekingduck/commands/nodes.py
peekingduck/configs/node_template.yml
peekingduck/configs/augment/brightness.yml
peekingduck/configs/augment/contrast.yml
peekingduck/configs/augment/undistort.yml
peekingduck/configs/dabble/bbox_count.yml
peekingduck/configs/dabble/bbox_to_3d_loc.yml
peekingduck/configs/dabble/bbox_to_btm_midpoint.yml
peekingduck/configs/dabble/camera_calibration.yml
peekingduck/configs/dabble/check_large_groups.yml
peekingduck/configs/dabble/check_nearby_objs.yml
peekingduck/configs/dabble/fps.yml
peekingduck/configs/dabble/group_nearby_objs.yml
peekingduck/configs/dabble/keypoints_to_3d_loc.yml
peekingduck/configs/dabble/statistics.yml
peekingduck/configs/dabble/tracking.yml
peekingduck/configs/dabble/zone_count.yml
peekingduck/configs/draw/bbox.yml
peekingduck/configs/draw/blur_bbox.yml
peekingduck/configs/draw/btm_midpoint.yml
peekingduck/configs/draw/group_bbox_and_tag.yml
peekingduck/configs/draw/heat_map.yml
peekingduck/configs/draw/instance_mask.yml
peekingduck/configs/draw/legend.yml
peekingduck/configs/draw/mosaic_bbox.yml
peekingduck/configs/draw/poses.yml
peekingduck/configs/draw/tag.yml
peekingduck/configs/draw/zones.yml
peekingduck/configs/input/visual.yml
peekingduck/configs/model/csrnet.yml
peekingduck/configs/model/efficientdet.yml
peekingduck/configs/model/fairmot.yml
peekingduck/configs/model/hrnet.yml
peekingduck/configs/model/jde.yml
peekingduck/configs/model/mask_rcnn.yml
peekingduck/configs/model/movenet.yml
peekingduck/configs/model/mtcnn.yml
peekingduck/configs/model/posenet.yml
peekingduck/configs/model/yolact_edge.yml
peekingduck/configs/model/yolo.yml
peekingduck/configs/model/yolo_face.yml
peekingduck-1.3.0.post1.dist-info/LICENSE
peekingduck-1.3.0.post1.dist-info/METADATA
peekingduck-1.3.0.post1.dist-info/WHEEL
peekingduck-1.3.0.post1.dist-info/entry_points.txt
peekingduck-1.3.0.post1.dist-info/top_level.txt
peekingduck-1.3.0.post1.dist-info/RECORD
