Metadata-Version: 2.1
Name: peekingduck
Version: 1.3.0.post1
Summary: A modular framework built to simplify Computer Vision inference workloads.
Home-page: https://github.com/aisingapore/PeekingDuck
Author: 'AI Singapore'
Author-email: cvhub-ext@aisingapore.org
Keywords: 'peekingduck','computer vision','inference','edge'
Classifier: Development Status :: 4 - Beta
Classifier: Programming Language :: Python :: 3.6
Classifier: Programming Language :: Python :: 3.7
Classifier: Programming Language :: Python :: 3.8
Classifier: Programming Language :: Python :: 3.9
Classifier: License :: OSI Approved :: Apache Software License
Classifier: Operating System :: OS Independent
Classifier: Topic :: Scientific/Engineering :: Artificial Intelligence
Classifier: Topic :: Software Development :: Libraries :: Python Modules
Requires-Python: <3.10,>=3.6
License-File: LICENSE
Requires-Dist: pyyaml (>=5.3)
Requires-Dist: click (==7.1.2)
Requires-Dist: requests (==2.24)
Requires-Dist: opencv-contrib-python (>=4.5.2.54)
Requires-Dist: protobuf (<=3.20.1)
Requires-Dist: tensorflow (<2.8,>=2.2)
Requires-Dist: numpy (>=1.17.3)
Requires-Dist: tqdm (==4.45.0)
Requires-Dist: colorama (==0.4.4)
Requires-Dist: torch (==1.10.0)
Requires-Dist: torchvision (==0.11.1)
Requires-Dist: typeguard (>=2.13.3)
Requires-Dist: scipy (>=1.4.1)
